[
  {
    "Águas Lindas de Goiás": {
      "instalado_em": "01/01/1997", 
      "area": "188,385 km", 
      "bioma": "Cerrado", 
      "populacao": "159.378 hab."
    }
  }
,
  {
    "Abadiânia": {
      "instalado_em": "01/01/1954", 
      "area": "1.045,127 km", 
      "bioma": "Cerrado", 
      "populacao": "15.757 hab."
    }
  }
,
  {
    "Adelândia": {
      "instalado_em": "01/06/1989", 
      "area": "115,353 km", 
      "bioma": "Cerrado", 
      "populacao": "2.477 hab."
    }
  }
,
  {
    "Alexânia": {
      "instalado_em": "01/01/1959", 
      "area": "847,893 km", 
      "bioma": "Cerrado", 
      "populacao": "23.814 hab."
    }
  }
,
  {
    "Água Limpa": {
      "instalado_em": "01/03/1959", 
      "area": "452,858 km", 
      "bioma": "Cerrado e Mata Atlântica", 
      "populacao": "2.013 hab."
    }
  }
,
  {
    "Água Fria de Goiás": {
      "instalado_em": "01/06/1989", 
      "area": "2.029,416 km", 
      "bioma": "Cerrado", 
      "populacao": "5.090 hab."
    }
  }
,
  {
    "Abadia de Goiás": {
      "instalado_em": "01/01/1997", 
      "area": "146,778 km", 
      "bioma": "Cerrado", 
      "populacao": "6.876 hab."
    }
  }
,
  {
    "Aloândia": {
      "instalado_em": "01/01/1954", 
      "area": "102,160 km", 
      "bioma": "Cerrado", 
      "populacao": "2.051 hab."
    }
  }
,
  {
    "Alto Horizonte": {
      "instalado_em": "01/01/1993", 
      "area": "503,764 km", 
      "bioma": "Cerrado", 
      "populacao": "4.505 hab."
    }
  }
,
  {
    "Alto Paraíso de Goiás": {
      "instalado_em": "12/10/1953", 
      "area": "2.593,905 km", 
      "bioma": "Cerrado", 
      "populacao": "6.885 hab."
    }
  }
,
  {
    "Alvorada do Norte": {
      "instalado_em": "01/01/1964", 
      "area": "1.259,366 km", 
      "bioma": "Cerrado", 
      "populacao": "8.084 hab."
    }
  }
,
  {
    "Americano do Brasil": {
      "instalado_em": "01/02/1983", 
      "area": "133,563 km", 
      "bioma": "Cerrado", 
      "populacao": "5.508 hab."
    }
  }
,
  {
    "Anápolis": {
      "instalado_em": "01/01/1939", 
      "area": "933,156 km", 
      "bioma": "Cerrado", 
      "populacao": "334.613 hab."
    }
  }
,
  {
    "Acreúna": {
      "instalado_em": "31/01/1977", 
      "area": "1.565,997 km", 
      "bioma": "Cerrado", 
      "populacao": "20.279 hab."
    }
  }
,
  {
    "Anhanguera": {
      "instalado_em": "01/01/1955", 
      "area": "56,950 km", 
      "bioma": "Cerrado e Mata Atlântica", 
      "populacao": "1.020 hab."
    }
  }
,
  {
    "Aparecida de Goiânia": {
      "instalado_em": "01/01/1964", 
      "area": "288,122 km", 
      "bioma": "Cerrado", 
      "populacao": "455.657 hab."
    }
  }
,
  {
    "Aparecida do Rio Doce": {
      "instalado_em": "01/01/1993", 
      "area": "602,133 km", 
      "bioma": "Cerrado", 
      "populacao": "2.427 hab."
    }
  }
,
  {
    "Aragarças": {
      "instalado_em": "01/01/1954", 
      "area": "662,890 km", 
      "bioma": "Cerrado", 
      "populacao": "18.305 hab."
    }
  }
,
  {
    "Araçu": {
      "instalado_em": "01/01/1959", 
      "area": "148,936 km", 
      "bioma": "Cerrado", 
      "populacao": "3.802 hab."
    }
  }
,
  {
    "Aporé": {
      "instalado_em": "01/01/1959", 
      "area": "2.900,055 km", 
      "bioma": "Cerrado", 
      "populacao": "3.803 hab."
    }
  }
,
  {
    "Aragoiânia": {
      "instalado_em": "01/01/1959", 
      "area": "219,550 km", 
      "bioma": "Cerrado", 
      "populacao": "8.365 hab."
    }
  }
,
  {
    "Amaralina": {
      "instalado_em": "01/01/1997", 
      "area": "1.343,174 km", 
      "bioma": "Cerrado", 
      "populacao": "3.434 hab."
    }
  }
,
  {
    "Araguapaz": {
      "instalado_em": "01/02/1983", 
      "area": "2.193,700 km", 
      "bioma": "Cerrado", 
      "populacao": "7.510 hab."
    }
  }
,
  {
    "Arenópolis": {
      "instalado_em": "01/02/1983", 
      "area": "1.074,595 km", 
      "bioma": "Cerrado", 
      "populacao": "3.277 hab."
    }
  }
,
  {
    "Amorinópolis": {
      "instalado_em": "01/01/1959", 
      "area": "408,525 km", 
      "bioma": "Cerrado", 
      "populacao": "3.609 hab."
    }
  }
,
  {
    "Aurilândia": {
      "instalado_em": "01/01/1949", 
      "area": "565,340 km", 
      "bioma": "Cerrado", 
      "populacao": "3.650 hab."
    }
  }
,
  {
    "Aruanã": {
      "instalado_em": "29/01/1959", 
      "area": "3.050,306 km", 
      "bioma": "Cerrado", 
      "populacao": "7.496 hab."
    }
  }
,
  {
    "Avelinópolis": {
      "instalado_em": "01/01/1964", 
      "area": "173,640 km", 
      "bioma": "Cerrado", 
      "populacao": "2.450 hab."
    }
  }
,
  {
    "Barro Alto": {
      "instalado_em": "01/01/1959", 
      "area": "1.093,248 km", 
      "bioma": "Cerrado", 
      "populacao": "8.716 hab."
    }
  }
,
  {
    "Baliza": {
      "instalado_em": "01/01/1944", 
      "area": "1.782,596 km", 
      "bioma": "Cerrado", 
      "populacao": "3.714 hab."
    }
  }
,
  {
    "Bom Jardim de Goiás": {
      "instalado_em": "01/01/1954", 
      "area": "1.899,506 km", 
      "bioma": "Cerrado", 
      "populacao": "8.423 hab."
    }
  }
,
  {
    "Bela Vista de Goiás": {
      "instalado_em": "01/01/1939", 
      "area": "1.253,414 km", 
      "bioma": "Cerrado", 
      "populacao": "24.554 hab."
    }
  }
,
  {
    "Bom Jesus de Goiás": {
      "instalado_em": "01/01/1964", 
      "area": "1.405,119 km", 
      "bioma": "Cerrado e Mata Atlântica", 
      "populacao": "20.727 hab."
    }
  }
,
  {
    "Anicuns": {
      "instalado_em": "01/01/1939", 
      "area": "979,230 km", 
      "bioma": "Cerrado", 
      "populacao": "20.239 hab."
    }
  }
,
  {
    "Bonfinópolis": {
      "instalado_em": "01/06/1989", 
      "area": "122,389 km", 
      "bioma": "Cerrado", 
      "populacao": "7.536 hab."
    }
  }
,
  {
    "Britânia": {
      "instalado_em": "25/01/1964", 
      "area": "1.461,187 km", 
      "bioma": "Cerrado", 
      "populacao": "5.509 hab."
    }
  }
,
  {
    "Buriti de Goiás": {
      "instalado_em": "01/01/1993", 
      "area": "199,292 km", 
      "bioma": "Cerrado", 
      "populacao": "2.560 hab."
    }
  }
,
  {
    "Cabeceiras": {
      "instalado_em": "20/03/1960", 
      "area": "1.127,599 km", 
      "bioma": "Cerrado", 
      "populacao": "7.354 hab."
    }
  }
,
  {
    "Cachoeira Alta": {
      "instalado_em": "01/01/1954", 
      "area": "1.654,554 km", 
      "bioma": "Cerrado e Mata Atlântica", 
      "populacao": "10.553 hab."
    }
  }
,
  {
    "Cachoeira Dourada": {
      "instalado_em": "01/02/1983", 
      "area": "521,134 km", 
      "bioma": "Cerrado e Mata Atlântica", 
      "populacao": "8.254 hab."
    }
  }
,
  {
    "Bonópolis": {
      "instalado_em": "01/01/1997", 
      "area": "1.628,486 km", 
      "bioma": "Cerrado", 
      "populacao": "3.503 hab."
    }
  }
,
  {
    "Caçu": {
      "instalado_em": "01/01/1954", 
      "area": "2.251,007 km", 
      "bioma": "Cerrado e Mata Atlântica", 
      "populacao": "13.283 hab."
    }
  }
,
  {
    "Caiapônia": {
      "instalado_em": "01/01/1939", 
      "area": "8.637,871 km", 
      "bioma": "Cerrado", 
      "populacao": "16.757 hab."
    }
  }
,
  {
    "Caldas Novas": {
      "instalado_em": "01/01/1939", 
      "area": "1.595,966 km", 
      "bioma": "Cerrado e Mata Atlântica", 
      "populacao": "70.473 hab."
    }
  }
,
  {
    "Caldazinha": {
      "instalado_em": "01/01/1993", 
      "area": "249,691 km", 
      "bioma": "Cerrado", 
      "populacao": "3.325 hab."
    }
  }
,
  {
    "Buriti Alegre": {
      "instalado_em": "01/01/1939", 
      "area": "895,456 km", 
      "bioma": "Cerrado e Mata Atlântica", 
      "populacao": "9.054 hab."
    }
  }
,
  {
    "Buritinópolis": {
      "instalado_em": "01/01/1993", 
      "area": "247,047 km", 
      "bioma": "Cerrado", 
      "populacao": "3.321 hab."
    }
  }
,
  {
    "Campinaçu": {
      "instalado_em": "01/02/1983", 
      "area": "1.974,375 km", 
      "bioma": "Cerrado", 
      "populacao": "3.656 hab."
    }
  }
,
  {
    "Campestre de Goiás": {
      "instalado_em": "01/01/1964", 
      "area": "273,815 km", 
      "bioma": "Cerrado", 
      "populacao": "3.387 hab."
    }
  }
,
  {
    "Campinorte": {
      "instalado_em": "01/01/1964", 
      "area": "1.067,197 km", 
      "bioma": "Cerrado", 
      "populacao": "11.111 hab."
    }
  }
,
  {
    "Cachoeira de Goiás": {
      "instalado_em": "01/01/1954", 
      "area": "422,751 km", 
      "bioma": "Cerrado", 
      "populacao": "1.417 hab."
    }
  }
,
  {
    "Campo Alegre de Goiás": {
      "instalado_em": "01/01/1954", 
      "area": "2.462,993 km", 
      "bioma": "Cerrado", 
      "populacao": "6.060 hab."
    }
  }
,
  {
    "Campo Limpo de Goiás": {
      "instalado_em": "01/01/2001", 
      "area": "159,557 km", 
      "bioma": "Cerrado", 
      "populacao": "6.241 hab."
    }
  }
,
  {
    "Campos Belos": {
      "instalado_em": "01/01/1954", 
      "area": "724,068 km", 
      "bioma": "Cerrado", 
      "populacao": "18.410 hab."
    }
  }
,
  {
    "Castelândia": {
      "instalado_em": "01/01/1993", 
      "area": "297,428 km", 
      "bioma": "Cerrado e Mata Atlântica", 
      "populacao": "3.638 hab."
    }
  }
,
  {
    "Campos Verdes": {
      "instalado_em": "01/01/1989", 
      "area": "441,645 km", 
      "bioma": "Cerrado", 
      "populacao": "5.020 hab."
    }
  }
,
  {
    "Catalão": {
      "instalado_em": "01/01/1939", 
      "area": "3.821,463 km", 
      "bioma": "Cerrado e Mata Atlântica", 
      "populacao": "86.647 hab."
    }
  }
,
  {
    "Cavalcante": {
      "instalado_em": "01/01/1939", 
      "area": "6.953,666 km", 
      "bioma": "Cerrado", 
      "populacao": "9.392 hab."
    }
  }
,
  {
    "Caturaí": {
      "instalado_em": "01/01/1959", 
      "area": "207,264 km", 
      "bioma": "Cerrado", 
      "populacao": "4.686 hab."
    }
  }
,
  {
    "Cezarina": {
      "instalado_em": "01/01/1989", 
      "area": "415,811 km", 
      "bioma": "Cerrado", 
      "populacao": "7.545 hab."
    }
  }
,
  {
    "Ceres": {
      "instalado_em": "01/01/1954", 
      "area": "214,322 km", 
      "bioma": "Cerrado", 
      "populacao": "20.722 hab."
    }
  }
,
  {
    "Cidade Ocidental": {
      "instalado_em": "01/01/1993", 
      "area": "390,000 km", 
      "bioma": "Cerrado", 
      "populacao": "55.915 hab."
    }
  }
,
  {
    "Colinas do Sul": {
      "instalado_em": "01/06/1989", 
      "area": "1.708,187 km", 
      "bioma": "Cerrado", 
      "populacao": "3.523 hab."
    }
  }
,
  {
    "Cocalzinho de Goiás": {
      "instalado_em": "01/01/1993", 
      "area": "1.789,039 km", 
      "bioma": "Cerrado", 
      "populacao": "17.407 hab."
    }
  }
,
  {
    "Córrego do Ouro": {
      "instalado_em": "01/01/1954", 
      "area": "462,304 km", 
      "bioma": "Cerrado", 
      "populacao": "2.632 hab."
    }
  }
,
  {
    "Cristalina": {
      "instalado_em": "01/01/1939", 
      "area": "6.162,097 km", 
      "bioma": "Cerrado", 
      "populacao": "46.580 hab."
    }
  }
,
  {
    "Carmo do Rio Verde": {
      "instalado_em": "01/01/1954", 
      "area": "418,544 km", 
      "bioma": "Cerrado", 
      "populacao": "8.928 hab."
    }
  }
,
  {
    "Cristianópolis": {
      "instalado_em": "01/01/1954", 
      "area": "225,359 km", 
      "bioma": "Cerrado", 
      "populacao": "2.932 hab."
    }
  }
,
  {
    "Crixás": {
      "instalado_em": "01/01/1954", 
      "area": "4.661,162 km", 
      "bioma": "Cerrado", 
      "populacao": "15.760 hab."
    }
  }
,
  {
    "Chapadão do Céu": {
      "instalado_em": "01/01/1993", 
      "area": "2.185,124 km", 
      "bioma": "Cerrado", 
      "populacao": "7.001 hab."
    }
  }
,
  {
    "Cromínia": {
      "instalado_em": "01/01/1954", 
      "area": "364,105 km", 
      "bioma": "Cerrado", 
      "populacao": "3.555 hab."
    }
  }
,
  {
    "Damianópolis": {
      "instalado_em": "01/01/1959", 
      "area": "415,349 km", 
      "bioma": "Cerrado", 
      "populacao": "3.292 hab."
    }
  }
,
  {
    "Cumari": {
      "instalado_em": "01/01/1949", 
      "area": "570,542 km", 
      "bioma": "Cerrado e Mata Atlântica", 
      "populacao": "2.964 hab."
    }
  }
,
  {
    "Damolândia": {
      "instalado_em": "01/01/1959", 
      "area": "84,495 km", 
      "bioma": "Cerrado", 
      "populacao": "2.747 hab."
    }
  }
,
  {
    "Corumbá de Goiás": {
      "instalado_em": "01/01/1939", 
      "area": "1.061,955 km", 
      "bioma": "Cerrado", 
      "populacao": "10.361 hab."
    }
  }
,
  {
    "Brazabrantes": {
      "instalado_em": "01/01/1959", 
      "area": "123,072 km", 
      "bioma": "Cerrado", 
      "populacao": "3.232 hab."
    }
  }
,
  {
    "Davinópolis": {
      "instalado_em": "01/01/1964", 
      "area": "481,296 km", 
      "bioma": "Cerrado e Mata Atlântica", 
      "populacao": "2.056 hab."
    }
  }
,
  {
    "Diorama": {
      "instalado_em": "01/01/1959", 
      "area": "687,348 km", 
      "bioma": "Cerrado", 
      "populacao": "2.479 hab."
    }
  }
,
  {
    "Corumbaíba": {
      "instalado_em": "01/01/1939", 
      "area": "1.883,665 km", 
      "bioma": "Cerrado e Mata Atlântica", 
      "populacao": "8.181 hab."
    }
  }
,
  {
    "Divinópolis de Goiás": {
      "instalado_em": "01/01/1959", 
      "area": "830,974 km", 
      "bioma": "Cerrado", 
      "populacao": "4.962 hab."
    }
  }
,
  {
    "Doverlândia": {
      "instalado_em": "01/02/1983", 
      "area": "3.222,941 km", 
      "bioma": "Cerrado", 
      "populacao": "7.892 hab."
    }
  }
,
  {
    "Estrela do Norte": {
      "instalado_em": "01/01/1959", 
      "area": "301,642 km", 
      "bioma": "Cerrado", 
      "populacao": "3.320 hab."
    }
  }
,
  {
    "Faina": {
      "instalado_em": "01/06/1989", 
      "area": "1.945,658 km", 
      "bioma": "Cerrado", 
      "populacao": "6.983 hab."
    }
  }
,
  {
    "Fazenda Nova": {
      "instalado_em": "01/01/1954", 
      "area": "1.281,420 km", 
      "bioma": "Cerrado", 
      "populacao": "6.322 hab."
    }
  }
,
  {
    "Firminópolis": {
      "instalado_em": "01/01/1949", 
      "area": "423,649 km", 
      "bioma": "Cerrado", 
      "populacao": "11.580 hab."
    }
  }
,
  {
    "Flores de Goiás": {
      "instalado_em": "01/01/1964", 
      "area": "3.709,427 km", 
      "bioma": "Cerrado", 
      "populacao": "12.066 hab."
    }
  }
,
  {
    "Formoso": {
      "instalado_em": "01/01/1964", 
      "area": "844,289 km", 
      "bioma": "Cerrado", 
      "populacao": "4.883 hab."
    }
  }
,
  {
    "Goianápolis": {
      "instalado_em": "01/01/1959", 
      "area": "162,435 km", 
      "bioma": "Cerrado", 
      "populacao": "10.695 hab."
    }
  }
,
  {
    "Gameleira de Goiás": {
      "instalado_em": "01/01/2001", 
      "area": "591,995 km", 
      "bioma": "Cerrado", 
      "populacao": "3.275 hab."
    }
  }
,
  {
    "Goiandira": {
      "instalado_em": "01/01/1939", 
      "area": "564,687 km", 
      "bioma": "Cerrado e Mata Atlântica", 
      "populacao": "5.265 hab."
    }
  }
,
  {
    "Goianésia": {
      "instalado_em": "01/01/1954", 
      "area": "1.547,274 km", 
      "bioma": "Cerrado", 
      "populacao": "59.549 hab."
    }
  }
,
  {
    "Goiânia": {
      "instalado_em": "01/01/1939", 
      "area": "733,116 km", 
      "bioma": "Cerrado", 
      "populacao": "1.302.001 hab."
    }
  }
,
  {
    "Edealina": {
      "instalado_em": "01/01/1989", 
      "area": "603,654 km", 
      "bioma": "Cerrado", 
      "populacao": "3.733 hab."
    }
  }
,
  {
    "Edéia": {
      "instalado_em": "01/01/1949", 
      "area": "1.461,503 km", 
      "bioma": "Cerrado", 
      "populacao": "11.266 hab."
    }
  }
,
  {
    "Goiás": {
      "instalado_em": "01/01/1939", 
      "area": "3.108,019 km", 
      "bioma": "Cerrado", 
      "populacao": "24.727 hab."
    }
  }
,
  {
    "Goianira": {
      "instalado_em": "04/01/1959", 
      "area": "209,036 km", 
      "bioma": "Cerrado", 
      "populacao": "34.060 hab."
    }
  }
,
  {
    "Goiatuba": {
      "instalado_em": "01/01/1939", 
      "area": "2.475,112 km", 
      "bioma": "Cerrado e Mata Atlântica", 
      "populacao": "32.492 hab."
    }
  }
,
  {
    "Gouvelândia": {
      "instalado_em": "01/06/1989", 
      "area": "824,260 km", 
      "bioma": "Cerrado e Mata Atlântica", 
      "populacao": "4.949 hab."
    }
  }
,
  {
    "Guapó": {
      "instalado_em": "01/01/1949", 
      "area": "516,844 km", 
      "bioma": "Cerrado", 
      "populacao": "13.976 hab."
    }
  }
,
  {
    "Guaraíta": {
      "instalado_em": "01/01/1993", 
      "area": "205,307 km", 
      "bioma": "Cerrado", 
      "populacao": "2.376 hab."
    }
  }
,
  {
    "Formosa": {
      "instalado_em": "01/01/1939", 
      "area": "5.811,788 km", 
      "bioma": "Cerrado", 
      "populacao": "100.085 hab."
    }
  }
,
  {
    "Guarani de Goiás": {
      "instalado_em": "01/01/1964", 
      "area": "1.229,148 km", 
      "bioma": "Cerrado", 
      "populacao": "4.258 hab."
    }
  }
,
  {
    "Heitoraí": {
      "instalado_em": "01/01/1964", 
      "area": "229,638 km", 
      "bioma": "Cerrado", 
      "populacao": "3.571 hab."
    }
  }
,
  {
    "Hidrolândia": {
      "instalado_em": "01/01/1949", 
      "area": "943,897 km", 
      "bioma": "Cerrado", 
      "populacao": "17.398 hab."
    }
  }
,
  {
    "Iaciara": {
      "instalado_em": "01/01/1959", 
      "area": "1.550,376 km", 
      "bioma": "Cerrado", 
      "populacao": "12.427 hab."
    }
  }
,
  {
    "Hidrolina": {
      "instalado_em": "01/01/1959", 
      "area": "580,391 km", 
      "bioma": "Cerrado", 
      "populacao": "4.029 hab."
    }
  }
,
  {
    "Indiara": {
      "instalado_em": "01/02/1983", 
      "area": "956,475 km", 
      "bioma": "Cerrado", 
      "populacao": "13.687 hab."
    }
  }
,
  {
    "Inaciolândia": {
      "instalado_em": "01/01/1993", 
      "area": "688,404 km", 
      "bioma": "Cerrado e Mata Atlântica", 
      "populacao": "5.699 hab."
    }
  }
,
  {
    "Inhumas": {
      "instalado_em": "01/01/1939", 
      "area": "613,226 km", 
      "bioma": "Cerrado", 
      "populacao": "48.246 hab."
    }
  }
,
  {
    "Ipameri": {
      "instalado_em": "01/01/1939", 
      "area": "4.368,991 km", 
      "bioma": "Cerrado", 
      "populacao": "24.735 hab."
    }
  }
,
  {
    "Ipiranga de Goiás": {
      "instalado_em": "01/01/2001", 
      "area": "241,289 km", 
      "bioma": "Cerrado", 
      "populacao": "2.844 hab."
    }
  }
,
  {
    "Israelândia": {
      "instalado_em": "01/01/1959", 
      "area": "577,482 km", 
      "bioma": "Cerrado", 
      "populacao": "2.887 hab."
    }
  }
,
  {
    "Itaguari": {
      "instalado_em": "01/01/1989", 
      "area": "146,638 km", 
      "bioma": "Cerrado", 
      "populacao": "4.513 hab."
    }
  }
,
  {
    "Itaguaru": {
      "instalado_em": "01/01/1959", 
      "area": "239,677 km", 
      "bioma": "Cerrado", 
      "populacao": "5.437 hab."
    }
  }
,
  {
    "Itapaci": {
      "instalado_em": "15/03/1939", 
      "area": "956,125 km", 
      "bioma": "Cerrado", 
      "populacao": "18.458 hab."
    }
  }
,
  {
    "Itapirapuã": {
      "instalado_em": "01/01/1959", 
      "area": "2.043,715 km", 
      "bioma": "Cerrado", 
      "populacao": "7.835 hab."
    }
  }
,
  {
    "Itapuranga": {
      "instalado_em": "01/01/1954", 
      "area": "1.276,479 km", 
      "bioma": "Cerrado", 
      "populacao": "26.125 hab."
    }
  }
,
  {
    "Itarumã": {
      "instalado_em": "01/01/1954", 
      "area": "3.433,626 km", 
      "bioma": "Cerrado e Mata Atlântica", 
      "populacao": "6.300 hab."
    }
  }
,
  {
    "Itauçu": {
      "instalado_em": "01/01/1949", 
      "area": "383,842 km", 
      "bioma": "Cerrado", 
      "populacao": "8.575 hab."
    }
  }
,
  {
    "Itumbiara": {
      "instalado_em": "01/01/1939", 
      "area": "2.462,930 km", 
      "bioma": "Cerrado e Mata Atlântica", 
      "populacao": "92.883 hab."
    }
  }
,
  {
    "Ivolândia": {
      "instalado_em": "01/01/1954", 
      "area": "1.257,663 km", 
      "bioma": "Cerrado", 
      "populacao": "2.663 hab."
    }
  }
,
  {
    "Jandaia": {
      "instalado_em": "01/01/1954", 
      "area": "864,106 km", 
      "bioma": "Cerrado", 
      "populacao": "6.164 hab."
    }
  }
,
  {
    "Iporá": {
      "instalado_em": "01/01/1949", 
      "area": "1.026,384 km", 
      "bioma": "Cerrado", 
      "populacao": "31.274 hab."
    }
  }
,
  {
    "Jaraguá": {
      "instalado_em": "01/01/1939", 
      "area": "1.849,552 km", 
      "bioma": "Cerrado", 
      "populacao": "41.870 hab."
    }
  }
,
  {
    "Jataí": {
      "instalado_em": "01/01/1939", 
      "area": "7.174,228 km", 
      "bioma": "Cerrado", 
      "populacao": "88.006 hab."
    }
  }
,
  {
    "Itaberaí": {
      "instalado_em": "01/01/1939", 
      "area": "1.457,280 km", 
      "bioma": "Cerrado", 
      "populacao": "35.371 hab."
    }
  }
,
  {
    "Jussara": {
      "instalado_em": "01/01/1959", 
      "area": "4.084,114 km", 
      "bioma": "Cerrado", 
      "populacao": "19.153 hab."
    }
  }
,
  {
    "Itajá": {
      "instalado_em": "01/01/1959", 
      "area": "2.091,397 km", 
      "bioma": "Cerrado e Mata Atlântica", 
      "populacao": "5.062 hab."
    }
  }
,
  {
    "Jaupaci": {
      "instalado_em": "01/01/1959", 
      "area": "527,103 km", 
      "bioma": "Cerrado", 
      "populacao": "3.000 hab."
    }
  }
,
  {
    "Joviânia": {
      "instalado_em": "01/01/1959", 
      "area": "445,487 km", 
      "bioma": "Cerrado", 
      "populacao": "7.118 hab."
    }
  }
,
  {
    "Jesúpolis": {
      "instalado_em": "01/01/1993", 
      "area": "122,475 km", 
      "bioma": "Cerrado", 
      "populacao": "2.300 hab."
    }
  }
,
  {
    "Lagoa Santa": {
      "instalado_em": "01/01/2001", 
      "area": "458,868 km", 
      "bioma": "Cerrado", 
      "populacao": "1.254 hab."
    }
  }
,
  {
    "Mairipotaba": {
      "instalado_em": "01/01/1954", 
      "area": "467,428 km", 
      "bioma": "Cerrado", 
      "populacao": "2.374 hab."
    }
  }
,
  {
    "Matrinchã": {
      "instalado_em": "01/06/1989", 
      "area": "1.150,894 km", 
      "bioma": "Cerrado", 
      "populacao": "4.414 hab."
    }
  }
,
  {
    "Marzagão": {
      "instalado_em": "01/01/1954", 
      "area": "222,428 km", 
      "bioma": "Cerrado e Mata Atlântica", 
      "populacao": "2.072 hab."
    }
  }
,
  {
    "Guarinos": {
      "instalado_em": "01/06/1989", 
      "area": "595,866 km", 
      "bioma": "Cerrado", 
      "populacao": "2.299 hab."
    }
  }
,
  {
    "Maurilândia": {
      "instalado_em": "01/01/1964", 
      "area": "389,697 km", 
      "bioma": "Cerrado", 
      "populacao": "11.521 hab."
    }
  }
,
  {
    "Mimoso de Goiás": {
      "instalado_em": "01/06/1989", 
      "area": "1.386,915 km", 
      "bioma": "Cerrado", 
      "populacao": "2.685 hab."
    }
  }
,
  {
    "Minaçu": {
      "instalado_em": "01/02/1977", 
      "area": "2.860,735 km", 
      "bioma": "Cerrado", 
      "populacao": "31.154 hab."
    }
  }
,
  {
    "Mineiros": {
      "instalado_em": "01/01/1939", 
      "area": "9.060,091 km", 
      "bioma": "Cerrado", 
      "populacao": "52.935 hab."
    }
  }
,
  {
    "Moiporá": {
      "instalado_em": "27/03/1960", 
      "area": "460,624 km", 
      "bioma": "Cerrado", 
      "populacao": "1.763 hab."
    }
  }
,
  {
    "Leopoldo de Bulhões": {
      "instalado_em": "01/01/1949", 
      "area": "480,891 km", 
      "bioma": "Cerrado", 
      "populacao": "7.882 hab."
    }
  }
,
  {
    "Luziânia": {
      "instalado_em": "01/01/1939", 
      "area": "3.961,122 km", 
      "bioma": "Cerrado", 
      "populacao": "174.531 hab."
    }
  }
,
  {
    "Monte Alegre de Goiás": {
      "instalado_em": "12/10/1947", 
      "area": "3.119,808 km", 
      "bioma": "Cerrado", 
      "populacao": "7.730 hab."
    }
  }
,
  {
    "Mara Rosa": {
      "instalado_em": "01/01/1954", 
      "area": "1.687,905 km", 
      "bioma": "Cerrado", 
      "populacao": "10.649 hab."
    }
  }
,
  {
    "Montes Claros de Goiás": {
      "instalado_em": "01/01/1964", 
      "area": "2.899,177 km", 
      "bioma": "Cerrado", 
      "populacao": "7.987 hab."
    }
  }
,
  {
    "Montividiu": {
      "instalado_em": "01/01/1989", 
      "area": "1.874,153 km", 
      "bioma": "Cerrado", 
      "populacao": "10.572 hab."
    }
  }
,
  {
    "Montividiu do Norte": {
      "instalado_em": "01/01/1993", 
      "area": "1.332,996 km", 
      "bioma": "Cerrado", 
      "populacao": "4.122 hab."
    }
  }
,
  {
    "Morrinhos": {
      "instalado_em": "01/01/1939", 
      "area": "2.846,199 km", 
      "bioma": "Cerrado e Mata Atlântica", 
      "populacao": "41.460 hab."
    }
  }
,
  {
    "Morro Agudo de Goiás": {
      "instalado_em": "01/01/1989", 
      "area": "282,616 km", 
      "bioma": "Cerrado", 
      "populacao": "2.356 hab."
    }
  }
,
  {
    "Mundo Novo": {
      "instalado_em": "01/02/1983", 
      "area": "2.146,651 km", 
      "bioma": "Cerrado", 
      "populacao": "6.438 hab."
    }
  }
,
  {
    "Mossâmedes": {
      "instalado_em": "01/01/1954", 
      "area": "684,452 km", 
      "bioma": "Cerrado", 
      "populacao": "5.007 hab."
    }
  }
,
  {
    "Mozarlândia": {
      "instalado_em": "01/01/1964", 
      "area": "1.734,364 km", 
      "bioma": "Cerrado", 
      "populacao": "13.404 hab."
    }
  }
,
  {
    "Nazário": {
      "instalado_em": "01/01/1949", 
      "area": "269,103 km", 
      "bioma": "Cerrado", 
      "populacao": "7.874 hab."
    }
  }
,
  {
    "Nerópolis": {
      "instalado_em": "01/01/1949", 
      "area": "204,217 km", 
      "bioma": "Cerrado", 
      "populacao": "24.210 hab."
    }
  }
,
  {
    "Nova América": {
      "instalado_em": "01/01/1959", 
      "area": "212,025 km", 
      "bioma": "Cerrado", 
      "populacao": "2.259 hab."
    }
  }
,
  {
    "Nova Aurora": {
      "instalado_em": "01/01/1954", 
      "area": "302,655 km", 
      "bioma": "Cerrado e Mata Atlântica", 
      "populacao": "2.062 hab."
    }
  }
,
  {
    "Nova Glória": {
      "instalado_em": "01/02/1983", 
      "area": "412,953 km", 
      "bioma": "Cerrado", 
      "populacao": "8.508 hab."
    }
  }
,
  {
    "Nova Crixás": {
      "instalado_em": "01/02/1983", 
      "area": "7.298,781 km", 
      "bioma": "Cerrado", 
      "populacao": "11.927 hab."
    }
  }
,
  {
    "Nova Iguaçu de Goiás": {
      "instalado_em": "01/01/1993", 
      "area": "628,444 km", 
      "bioma": "Cerrado", 
      "populacao": "2.826 hab."
    }
  }
,
  {
    "Nova Roma": {
      "instalado_em": "01/01/1959", 
      "area": "2.135,960 km", 
      "bioma": "Cerrado", 
      "populacao": "3.471 hab."
    }
  }
,
  {
    "Nova Veneza": {
      "instalado_em": "01/01/1959", 
      "area": "123,377 km", 
      "bioma": "Cerrado", 
      "populacao": "8.129 hab."
    }
  }
,
  {
    "Novo Gama": {
      "instalado_em": "01/01/1997", 
      "area": "194,992 km", 
      "bioma": "Cerrado", 
      "populacao": "95.018 hab."
    }
  }
,
  {
    "Novo Planalto": {
      "instalado_em": "01/06/1989", 
      "area": "1.242,818 km", 
      "bioma": "Cerrado", 
      "populacao": "3.956 hab."
    }
  }
,
  {
    "Orizona": {
      "instalado_em": "01/01/1939", 
      "area": "1.972,884 km", 
      "bioma": "Cerrado", 
      "populacao": "14.300 hab."
    }
  }
,
  {
    "Niquelândia": {
      "instalado_em": "01/01/1939", 
      "area": "9.843,247 km", 
      "bioma": "Cerrado", 
      "populacao": "42.361 hab."
    }
  }
,
  {
    "Ouro Verde de Goiás": {
      "instalado_em": "01/01/1964", 
      "area": "208,769 km", 
      "bioma": "Cerrado", 
      "populacao": "4.034 hab."
    }
  }
,
  {
    "Ouvidor": {
      "instalado_em": "01/01/1954", 
      "area": "413,784 km", 
      "bioma": "Cerrado e Mata Atlântica", 
      "populacao": "5.467 hab."
    }
  }
,
  {
    "Padre Bernardo": {
      "instalado_em": "09/05/1964", 
      "area": "3.139,175 km", 
      "bioma": "Cerrado", 
      "populacao": "27.671 hab."
    }
  }
,
  {
    "Mambaí": {
      "instalado_em": "01/01/1959", 
      "area": "880,624 km", 
      "bioma": "Cerrado", 
      "populacao": "6.871 hab."
    }
  }
,
  {
    "Palmeiras de Goiás": {
      "instalado_em": "01/01/1939", 
      "area": "1.539,693 km", 
      "bioma": "Cerrado", 
      "populacao": "23.338 hab."
    }
  }
,
  {
    "Palmelo": {
      "instalado_em": "01/01/1954", 
      "area": "58,959 km", 
      "bioma": "Cerrado", 
      "populacao": "2.335 hab."
    }
  }
,
  {
    "Palminópolis": {
      "instalado_em": "01/01/1964", 
      "area": "387,693 km", 
      "bioma": "Cerrado", 
      "populacao": "3.557 hab."
    }
  }
,
  {
    "Panamá": {
      "instalado_em": "01/01/1954", 
      "area": "433,761 km", 
      "bioma": "Cerrado e Mata Atlântica", 
      "populacao": "2.682 hab."
    }
  }
,
  {
    "Perolândia": {
      "instalado_em": "01/01/1993", 
      "area": "1.029,624 km", 
      "bioma": "Cerrado", 
      "populacao": "2.950 hab."
    }
  }
,
  {
    "Novo Brasil": {
      "instalado_em": "01/01/1959", 
      "area": "649,954 km", 
      "bioma": "Cerrado", 
      "populacao": "3.519 hab."
    }
  }
,
  {
    "Petrolina de Goiás": {
      "instalado_em": "01/01/1949", 
      "area": "531,300 km", 
      "bioma": "Cerrado", 
      "populacao": "10.283 hab."
    }
  }
,
  {
    "Palestina de Goiás": {
      "instalado_em": "01/01/1989", 
      "area": "1.320,687 km", 
      "bioma": "Cerrado", 
      "populacao": "3.371 hab."
    }
  }
,
  {
    "Piracanjuba": {
      "instalado_em": "01/01/1939", 
      "area": "2.403,167 km", 
      "bioma": "Cerrado", 
      "populacao": "24.026 hab."
    }
  }
,
  {
    "Piranhas": {
      "instalado_em": "01/01/1954", 
      "area": "2.047,765 km", 
      "bioma": "Cerrado", 
      "populacao": "11.266 hab."
    }
  }
,
  {
    "Pilar de Goiás": {
      "instalado_em": "01/01/1954", 
      "area": "906,650 km", 
      "bioma": "Cerrado", 
      "populacao": "2.773 hab."
    }
  }
,
  {
    "Paranaiguara": {
      "instalado_em": "01/01/1954", 
      "area": "1.153,833 km", 
      "bioma": "Cerrado e Mata Atlântica", 
      "populacao": "9.100 hab."
    }
  }
,
  {
    "Paraúna": {
      "instalado_em": "01/01/1939", 
      "area": "3.779,385 km", 
      "bioma": "Cerrado", 
      "populacao": "10.863 hab."
    }
  }
,
  {
    "Pontalina": {
      "instalado_em": "01/01/1939", 
      "area": "1.436,954 km", 
      "bioma": "Cerrado", 
      "populacao": "17.121 hab."
    }
  }
,
  {
    "Porangatu": {
      "instalado_em": "01/01/1949", 
      "area": "4.820,518 km", 
      "bioma": "Cerrado", 
      "populacao": "42.355 hab."
    }
  }
,
  {
    "Porteirão": {
      "instalado_em": "01/01/1997", 
      "area": "603,941 km", 
      "bioma": "Cerrado", 
      "populacao": "3.347 hab."
    }
  }
,
  {
    "Portelândia": {
      "instalado_em": "01/01/1964", 
      "area": "556,576 km", 
      "bioma": "Cerrado", 
      "populacao": "3.839 hab."
    }
  }
,
  {
    "Professor Jamil": {
      "instalado_em": "01/01/1993", 
      "area": "349,419 km", 
      "bioma": "Cerrado", 
      "populacao": "3.239 hab."
    }
  }
,
  {
    "Pirenópolis": {
      "instalado_em": "01/01/1939", 
      "area": "2.205,010 km", 
      "bioma": "Cerrado", 
      "populacao": "23.006 hab."
    }
  }
,
  {
    "Rianápolis": {
      "instalado_em": "01/01/1959", 
      "area": "159,255 km", 
      "bioma": "Cerrado", 
      "populacao": "4.566 hab."
    }
  }
,
  {
    "Planaltina": {
      "instalado_em": "01/01/1939", 
      "area": "2.543,677 km", 
      "bioma": "Cerrado", 
      "populacao": "81.649 hab."
    }
  }
,
  {
    "Rio Quente": {
      "instalado_em": "01/07/1989", 
      "area": "255,961 km", 
      "bioma": "Cerrado", 
      "populacao": "3.312 hab."
    }
  }
,
  {
    "Rio Verde": {
      "instalado_em": "01/01/1939", 
      "area": "8.379,659 km", 
      "bioma": "Cerrado", 
      "populacao": "176.424 hab."
    }
  }
,
  {
    "Rubiataba": {
      "instalado_em": "01/01/1954", 
      "area": "748,264 km", 
      "bioma": "Cerrado", 
      "populacao": "18.915 hab."
    }
  }
,
  {
    "Posse": {
      "instalado_em": "01/01/1939", 
      "area": "2.024,537 km", 
      "bioma": "Cerrado", 
      "populacao": "31.419 hab."
    }
  }
,
  {
    "Santa Bárbara de Goiás": {
      "instalado_em": "01/01/1964", 
      "area": "139,598 km", 
      "bioma": "Cerrado", 
      "populacao": "5.751 hab."
    }
  }
,
  {
    "Mutunópolis": {
      "instalado_em": "01/01/1959", 
      "area": "955,875 km", 
      "bioma": "Cerrado", 
      "populacao": "3.849 hab."
    }
  }
,
  {
    "Santa Fé de Goiás": {
      "instalado_em": "01/06/1989", 
      "area": "1.169,167 km", 
      "bioma": "Cerrado", 
      "populacao": "4.762 hab."
    }
  }
,
  {
    "Santa Cruz de Goiás": {
      "instalado_em": "01/01/1949", 
      "area": "1.108,962 km", 
      "bioma": "Cerrado", 
      "populacao": "3.142 hab."
    }
  }
,
  {
    "Quirinópolis": {
      "instalado_em": "22/01/1944", 
      "area": "3.786,694 km", 
      "bioma": "Cerrado e Mata Atlântica", 
      "populacao": "43.220 hab."
    }
  }
,
  {
    "Rialma": {
      "instalado_em": "01/01/1954", 
      "area": "268,466 km", 
      "bioma": "Cerrado", 
      "populacao": "10.523 hab."
    }
  }
,
  {
    "Santa Helena de Goiás": {
      "instalado_em": "01/01/1949", 
      "area": "1.141,389 km", 
      "bioma": "Cerrado", 
      "populacao": "36.469 hab."
    }
  }
,
  {
    "Santa Isabel": {
      "instalado_em": "01/02/1983", 
      "area": "807,204 km", 
      "bioma": "Cerrado", 
      "populacao": "3.686 hab."
    }
  }
,
  {
    "Santa Rita do Novo Destino": {
      "instalado_em": "01/01/1997", 
      "area": "956,041 km", 
      "bioma": "Cerrado", 
      "populacao": "3.173 hab."
    }
  }
,
  {
    "Santa Rosa de Goiás": {
      "instalado_em": "01/01/1959", 
      "area": "164,097 km", 
      "bioma": "Cerrado", 
      "populacao": "2.909 hab."
    }
  }
,
  {
    "Santa Rita do Araguaia": {
      "instalado_em": "01/01/1954", 
      "area": "1.361,773 km", 
      "bioma": "Cerrado", 
      "populacao": "6.924 hab."
    }
  }
,
  {
    "Santa Tereza de Goiás": {
      "instalado_em": "19/01/1964", 
      "area": "794,556 km", 
      "bioma": "Cerrado", 
      "populacao": "3.995 hab."
    }
  }
,
  {
    "Santa Terezinha de Goiás": {
      "instalado_em": "01/01/1964", 
      "area": "1.202,240 km", 
      "bioma": "Cerrado", 
      "populacao": "10.302 hab."
    }
  }
,
  {
    "Sanclerlândia": {
      "instalado_em": "01/01/1964", 
      "area": "496,825 km", 
      "bioma": "Cerrado", 
      "populacao": "7.550 hab."
    }
  }
,
  {
    "São Domingos": {
      "instalado_em": "01/01/1939", 
      "area": "3.295,737 km", 
      "bioma": "Cerrado", 
      "populacao": "11.272 hab."
    }
  }
,
  {
    "Santo Antônio de Goiás": {
      "instalado_em": "01/01/1993", 
      "area": "132,805 km", 
      "bioma": "Cerrado", 
      "populacao": "4.703 hab."
    }
  }
,
  {
    "Santo Antônio do Descoberto": {
      "instalado_em": "01/02/1983", 
      "area": "944,145 km", 
      "bioma": "Cerrado", 
      "populacao": "63.248 hab."
    }
  }
,
  {
    "São João da Paraúna": {
      "instalado_em": "01/06/1989", 
      "area": "287,825 km", 
      "bioma": "Cerrado", 
      "populacao": "1.689 hab."
    }
  }
,
  {
    "São Francisco de Goiás": {
      "instalado_em": "01/01/1954", 
      "area": "415,791 km", 
      "bioma": "Cerrado", 
      "populacao": "6.120 hab."
    }
  }
,
  {
    "São João d`Aliança": {
      "instalado_em": "01/01/1954", 
      "area": "3.327,379 km", 
      "bioma": "Cerrado", 
      "populacao": "10.257 hab."
    }
  }
,
  {
    "São Luís de Montes Belos": {
      "instalado_em": "01/01/1954", 
      "area": "825,999 km", 
      "bioma": "Cerrado", 
      "populacao": "30.034 hab."
    }
  }
,
  {
    "São Luíz do Norte": {
      "instalado_em": "01/06/1989", 
      "area": "586,058 km", 
      "bioma": "Cerrado", 
      "populacao": "4.617 hab."
    }
  }
,
  {
    "São Miguel do Araguaia": {
      "instalado_em": "01/01/1959", 
      "area": "6.144,407 km", 
      "bioma": "Cerrado", 
      "populacao": "22.283 hab."
    }
  }
,
  {
    "Santo Antônio da Barra": {
      "instalado_em": "01/01/1993", 
      "area": "451,598 km", 
      "bioma": "Cerrado", 
      "populacao": "4.423 hab."
    }
  }
,
  {
    "São Miguel do Passa Quatro": {
      "instalado_em": "01/01/1989", 
      "area": "537,785 km", 
      "bioma": "Cerrado", 
      "populacao": "3.757 hab."
    }
  }
,
  {
    "São Simão": {
      "instalado_em": "01/01/1959", 
      "area": "414,011 km", 
      "bioma": "Mata Atlântica", 
      "populacao": "17.088 hab."
    }
  }
,
  {
    "São Patrício": {
      "instalado_em": "01/01/1997", 
      "area": "171,957 km", 
      "bioma": "Cerrado", 
      "populacao": "1.991 hab."
    }
  }
,
  {
    "Senador Canedo": {
      "instalado_em": "01/06/1989", 
      "area": "248,291 km", 
      "bioma": "Cerrado", 
      "populacao": "84.443 hab."
    }
  }
,
  {
    "Serranópolis": {
      "instalado_em": "01/01/1959", 
      "area": "5.526,723 km", 
      "bioma": "Cerrado", 
      "populacao": "7.481 hab."
    }
  }
,
  {
    "Simolândia": {
      "instalado_em": "01/06/1989", 
      "area": "347,976 km", 
      "bioma": "Cerrado", 
      "populacao": "6.514 hab."
    }
  }
,
  {
    "Teresina de Goiás": {
      "instalado_em": "01/06/1989", 
      "area": "774,639 km", 
      "bioma": "Cerrado", 
      "populacao": "3.016 hab."
    }
  }
,
  {
    "Três Ranchos": {
      "instalado_em": "01/01/1954", 
      "area": "282,069 km", 
      "bioma": "Cerrado e Mata Atlântica", 
      "populacao": "2.819 hab."
    }
  }
,
  {
    "Taquaral de Goiás": {
      "instalado_em": "01/01/1964", 
      "area": "204,218 km", 
      "bioma": "Cerrado", 
      "populacao": "3.541 hab."
    }
  }
,
  {
    "Sítio d`Abadia": {
      "instalado_em": "01/01/1939", 
      "area": "1.598,346 km", 
      "bioma": "Cerrado", 
      "populacao": "2.825 hab."
    }
  }
,
  {
    "Trindade": {
      "instalado_em": "01/01/1944", 
      "area": "710,714 km", 
      "bioma": "Cerrado", 
      "populacao": "104.488 hab."
    }
  }
,
  {
    "Pires do Rio": {
      "instalado_em": "01/01/1939", 
      "area": "1.073,361 km", 
      "bioma": "Cerrado", 
      "populacao": "28.762 hab."
    }
  }
,
  {
    "Trombas": {
      "instalado_em": "01/06/1989", 
      "area": "799,125 km", 
      "bioma": "Cerrado", 
      "populacao": "3.452 hab."
    }
  }
,
  {
    "Turvânia": {
      "instalado_em": "01/01/1959", 
      "area": "480,775 km", 
      "bioma": "Cerrado", 
      "populacao": "4.839 hab."
    }
  }
,
  {
    "Uruaçu": {
      "instalado_em": "01/01/1939", 
      "area": "2.141,817 km", 
      "bioma": "Cerrado", 
      "populacao": "36.929 hab."
    }
  }
,
  {
    "Uirapuru": {
      "instalado_em": "01/01/1993", 
      "area": "1.153,475 km", 
      "bioma": "Cerrado", 
      "populacao": "2.933 hab."
    }
  }
,
  {
    "Uruana": {
      "instalado_em": "01/01/1949", 
      "area": "522,506 km", 
      "bioma": "Cerrado", 
      "populacao": "13.826 hab."
    }
  }
,
  {
    "Urutaí": {
      "instalado_em": "01/01/1949", 
      "area": "626,723 km", 
      "bioma": "Cerrado", 
      "populacao": "3.074 hab."
    }
  }
,
  {
    "Silvânia": {
      "instalado_em": "01/01/1939", 
      "area": "2.345,940 km", 
      "bioma": "Cerrado", 
      "populacao": "19.089 hab."
    }
  }
,
  {
    "Terezópolis de Goiás": {
      "instalado_em": "01/01/1993", 
      "area": "106,913 km", 
      "bioma": "Cerrado", 
      "populacao": "6.561 hab."
    }
  }
,
  {
    "Vianópolis": {
      "instalado_em": "01/01/1949", 
      "area": "954,284 km", 
      "bioma": "Cerrado", 
      "populacao": "12.548 hab."
    }
  }
,
  {
    "Vila Propício": {
      "instalado_em": "01/01/1997", 
      "area": "2.181,583 km", 
      "bioma": "Cerrado", 
      "populacao": "5.145 hab."
    }
  }
,
  {
    "Varjão": {
      "instalado_em": "01/01/1959", 
      "area": "519,194 km", 
      "bioma": "Cerrado", 
      "populacao": "3.659 hab."
    }
  }
,
  {
    "Vila Boa": {
      "instalado_em": "01/01/1993", 
      "area": "1.060,172 km", 
      "bioma": "Cerrado", 
      "populacao": "4.735 hab."
    }
  }
,
  {
    "Vicentinópolis": {
      "instalado_em": "01/02/1983", 
      "area": "737,256 km", 
      "bioma": "Cerrado", 
      "populacao": "7.371 hab."
    }
  }
,
  {
    "Turvelândia": {
      "instalado_em": "01/06/1989", 
      "area": "933,957 km", 
      "bioma": "Cerrado", 
      "populacao": "4.399 hab."
    }
  }
,
  {
    "Valparaíso de Goiás": {
      "instalado_em": "01/01/1997", 
      "area": "61,410 km", 
      "bioma": "Cerrado", 
      "populacao": "132.982 hab."
    }
  }
]